{
    "pmid": "34606929",
    "title": "Aligning tumor mutational burden (TMB) quantification across diagnostic platforms: phase II of the Friends of Cancer Research TMB Harmonization Project",
    "authors": [
	"D M Vega",
	"L M Yee",
	"L M McShane",
	"P M Williams",
	"L Chen",
	"T Vilimas",
	"D Fabrizio",
	"V Funari",
	"J Newberg",
	"L K Bruce",
	"S-J Chen  6",
	"J Baden",
	"J Carl Barrett",
	"P Beer",
	"M Butler",
	"J-H Cheng",
	"J Conroy",
	"D Cyanam",
	"K Eyring",
	"E Garcia",
	"G Green",
	"V R Gregersen",
	"M D Hellmann",
	"L A Keefer",
	"L Lasiter",
	"A J Lazar",
	"M-C Li",
	"L E MacConaill",
	"K Meier",
	"H Mellert",
	"S Pabla",
	"A Pallavajjalla",
	"G Pestano",
	"R Salgado",
	"R Samara",
	"E S Sokol",
	"P Stafford",
	"J Budczies",
	"A Stenzinger",
	"W Tom",
	"K C Valkenburg",
	"X Z Wang",
	"V Weigman",
	"M Xie",
	"Q Xie",
	"A Zehir",
	"C Zhao",
	"Y Zhao",
	"M D Stewart",
	"J Allen",
	"TMB Consortium"
    ],
    "month": 12,
    "year": 2021,
    "journal": "Annals of Oncology",
    "url": "https://www.sciencedirect.com/science/article/pii/S0923753421044951",
    "doi": "https://doi.org/10.1016/j.annonc.2021.09.016",
    "license": "CC BY-NC-ND 4.0",
    "license_url": "http://creativecommons.org/licenses/by-nc-nd/4.0/"
}
